skill_ovos_stop/LICENSE
skill_ovos_stop/MANIFEST.in
skill_ovos_stop/README.md
skill_ovos_stop/__init__.py
skill_ovos_stop/version.py
skill_ovos_stop/locale/de-de/StopKeyword.voc
skill_ovos_stop/locale/de-de/stop.intent
skill_ovos_stop/locale/en-us/StopKeyword.voc
skill_ovos_stop/locale/en-us/stop.intent
skill_ovos_stop/locale/es-es/StopKeyword.voc
skill_ovos_stop/locale/es-es/stop.intent
skill_ovos_stop/locale/fr-fr/StopKeyword.voc
skill_ovos_stop/locale/fr-fr/stop.intent
skill_ovos_stop/locale/it-it/StopKeyword.voc
skill_ovos_stop/locale/it-it/stop.intent
skill_ovos_stop/locale/pt-pt/StopKeyword.voc
skill_ovos_stop/locale/pt-pt/stop.intent
skill_ovos_stop/ovos_skill_stop.egg-info/PKG-INFO
skill_ovos_stop/ovos_skill_stop.egg-info/SOURCES.txt
skill_ovos_stop/ovos_skill_stop.egg-info/dependency_links.txt
skill_ovos_stop/ovos_skill_stop.egg-info/entry_points.txt
skill_ovos_stop/ovos_skill_stop.egg-info/requires.txt
skill_ovos_stop/ovos_skill_stop.egg-info/top_level.txt
skill_ovos_stop/res/desktop/skill-better-stop.desktop
skill_ovos_stop/res/desktop/skill.json
skill_ovos_stop/res/icon/stop.svg
ovos_skill_stop-0.2.1.dist-info/LICENSE
ovos_skill_stop-0.2.1.dist-info/METADATA
ovos_skill_stop-0.2.1.dist-info/WHEEL
ovos_skill_stop-0.2.1.dist-info/entry_points.txt
ovos_skill_stop-0.2.1.dist-info/top_level.txt
ovos_skill_stop-0.2.1.dist-info/RECORD
