Metadata-Version: 2.1
Name: ovos-skill-stop
Version: 0.2.1
Summary: ovos skill plugin
Home-page: https://github.com/OpenVoiceOS/skill-ovos-stop
Author: JarbasAi
Author-email: jarbasai@mailfence.com
License: Apache-2.0
Keywords: ovos skill plugin
Platform: UNKNOWN
Requires-Dist: ovos-utils (>=0.0.28,~=0.0)
Requires-Dist: ovos-workshop (>=0.0.11,~=0.0)
